cc_codechecker/__init__.py
cc_codechecker/__main__.py
cc_codechecker/challenge.py
cc_codechecker/codechecker.py
cc_codechecker/configurable.py
cc_codechecker/configuration.py
cc_codechecker/context.py
cc_codechecker/project.py
cc_codechecker/runner.py
cc_codechecker/runners/bash.py
cc_codechecker-0.1.13.dist-info/entry_points.txt
cc_codechecker-0.1.13.dist-info/LICENSE.rst
cc_codechecker-0.1.13.dist-info/LICENSES/MIT.txt
cc_codechecker-0.1.13.dist-info/LICENSE
cc_codechecker-0.1.13.dist-info/LICENSES/CC0-1.0.txt
cc_codechecker-0.1.13.dist-info/WHEEL
cc_codechecker-0.1.13.dist-info/METADATA
cc_codechecker-0.1.13.dist-info/RECORD
