Metadata-Version: 2.1
Name: cc-codechecker
Version: 0.1.13
Summary: Facilities to manage coding challenges.
License: GPL-3.0-only
Keywords: coding,challenge,yaml,project,facilities
Author: Daniele Tentoni
Author-email: daniele.tentoni.1996@gmail.com
Maintainer: Daniele Tentoni
Maintainer-email: daniele.tentoni.1996@gmail.com
Requires-Python: >=3.10.0,<4.0.0
Classifier: License :: OSI Approved :: GNU General Public License v3 (GPLv3)
Classifier: Programming Language :: Python :: 3
Classifier: Programming Language :: Python :: 3.10
Requires-Dist: PyYAML (>=6.0,<7.0)
Requires-Dist: python-semantic-release (>=7.24.0,<8.0.0)
